ask_sdk_model_runtime/__init__.py
ask_sdk_model_runtime/__version__.py
ask_sdk_model_runtime/api_client.py
ask_sdk_model_runtime/api_client_message.py
ask_sdk_model_runtime/api_client_request.py
ask_sdk_model_runtime/api_client_response.py
ask_sdk_model_runtime/api_configuration.py
ask_sdk_model_runtime/api_response.py
ask_sdk_model_runtime/authentication_configuration.py
ask_sdk_model_runtime/base_service_client.py
ask_sdk_model_runtime/exceptions.py
ask_sdk_model_runtime/py.typed
ask_sdk_model_runtime/serializer.py
ask_sdk_model_runtime/service_client_response.py
ask_sdk_model_runtime/utils.py
ask_sdk_model_runtime/lwa/__init__.py
ask_sdk_model_runtime/lwa/access_token.py
ask_sdk_model_runtime/lwa/access_token_request.py
ask_sdk_model_runtime/lwa/access_token_response.py
ask_sdk_model_runtime/lwa/error.py
ask_sdk_model_runtime/lwa/lwa_client.py
ask_sdk_model_runtime/lwa/py.typed
ask_sdk_model_runtime-1.0.1.dist-info/METADATA
ask_sdk_model_runtime-1.0.1.dist-info/WHEEL
ask_sdk_model_runtime-1.0.1.dist-info/top_level.txt
ask_sdk_model_runtime-1.0.1.dist-info/RECORD
