Metadata-Version: 1.2
Name: ask-sdk-model-runtime
Version: 1.0.1
Summary: The ASK SDK Model Runtime package provides common provides common implementations like Serializer, ApiClient, Authentication Configuration etc that is used by the SDK models.
Home-page: https://github.com/alexa/alexa-apis-for-python
Author: Alexa Skills Kit
Author-email: ask-sdk-dynamic@amazon.com
License: Apache 2.0
Keywords: ASK SDK Model Runtime,Alexa Skills Kit,Alexa,Model,Runtime
Platform: UNKNOWN
Classifier: Development Status :: 5 - Production/Stable
Classifier: Intended Audience :: Developers
Classifier: Natural Language :: English
Classifier: License :: OSI Approved :: Apache Software License
Classifier: Programming Language :: Python
Classifier: Programming Language :: Python :: 2
Classifier: Programming Language :: Python :: 2.7
Classifier: Programming Language :: Python :: 3
Classifier: Programming Language :: Python :: 3.6
Classifier: Programming Language :: Python :: 3.7
Requires-Python: >2.6, !=3.0.*, !=3.1.*, !=3.2.*, !=3.3.*, !=3.4.*, !=3.5.*
